fstack/__init__.py
fstack/entrypoint.py
fstack-0.1.0.dist-info/licenses/LICENSE
fstack-0.1.0.dist-info/METADATA
fstack-0.1.0.dist-info/WHEEL
fstack-0.1.0.dist-info/top_level.txt
fstack-0.1.0.dist-info/RECORD
