Metadata-Version: 2.4
Name: fstack
Version: 0.1.0
Summary: libreria para el proyecto de fstack
Home-page: https://github.com/tu_usuario/mi-libreria
Author: Felipe Andres Gonzalez Quintero
Author-email: felipeagq99@gmail.com
License: MIT
Classifier: Programming Language :: Python :: 3
Classifier: License :: OSI Approved :: MIT License
Classifier: Operating System :: OS Independent
Requires-Python: >=3.10
License-File: LICENSE
Dynamic: license-file
